LICENSE
README.md
setup.py
bacinet/__init__.py
bacinet/exceptions.py
bacinet/header_options.py
bacinet/headers.py
bacinet/middleware.py
bacinet/py.typed
bacinet.egg-info/PKG-INFO
bacinet.egg-info/SOURCES.txt
bacinet.egg-info/dependency_links.txt
bacinet.egg-info/requires.txt
bacinet.egg-info/top_level.txt