Metadata-Version: 2.1
Name: bacinet
Version: 0.0.6
Summary: Setting up security-relevant response headers in FastAPI
Home-page: https://github.com/hbel/bacinet
Author: Hendrik Belitz
Author-email: hendrik@hendrikbelitz.de
Project-URL: Homepage, https://github.com/hbel/bacinet
Keywords: FastAPI headers http
Classifier: Programming Language :: Python :: 3
Classifier: License :: OSI Approved :: MIT License
Classifier: Operating System :: OS Independent
Requires-Python: >=3.9
License-File: LICENSE
Requires-Dist: fastapi
